{
  "users": [
    {
      "email": "test@test.com11",
      "id": "1",
      "password": "testtesttest11111",
      "user": "abdalla",
      "letPeopleFindBlogByEmail": true,
      "emailAboutAccountActivity": true,
      "twoFactorAuthentication": true,
      "enableEndLessScrolling": false,
      "messagingSounds": false,
      "bestStuffFirst": false,
      "includeStuffInorbit": false,
      "EnableColorizedTags": false,
      "includeFollowedTagPosts": false,
      "notificationsSettings": {
        "EmailUserAboutNewFollowersBox": true,
        "EmailUserAboutNewRepliesBox": false,
        "EmailUserAboutNewMentionsBox": false,
        "EmailUserAboutNewAnsweredAsksBox": true,
        "NotificationSettingsFor": "From nobody",
        "ApplySettingsForAllBlogs": false
      }
    }
  ]
}